flexpay/__init__.py
pyflexpay-0.9.dist-info/LICENCE
pyflexpay-0.9.dist-info/METADATA
pyflexpay-0.9.dist-info/WHEEL
pyflexpay-0.9.dist-info/top_level.txt
pyflexpay-0.9.dist-info/RECORD
