Metadata-Version: 2.1
Name: pyflexpay
Version: 0.9
Summary: A Python SDK for the FlexPay API for Payments Aggregation
Home-page: https://github.com/TralahM/pyflexpay
Author: Tralah M Brian
Author-email: briantralah@gmail.com
License: GPLV3
Project-URL: Source, https://github.com/TralahM/pyflexpay
Project-URL: Tracker, https://github.com/TralahM/pyflexpay/issues
Project-URL: Documentation, https://github.com/TralahM/pyflexpay
Classifier: Environment :: Web Environment
Classifier: Intended Audience :: Developers
Classifier: License :: OSI Approved :: GNU General Public License v3 (GPLv3)
Classifier: Operating System :: OS Independent
Classifier: Programming Language :: Python
Classifier: Programming Language :: Python :: 3
Classifier: Programming Language :: Python :: 3 :: Only
Classifier: Programming Language :: Python :: 3.6
Classifier: Programming Language :: Python :: 3.7
Classifier: Programming Language :: Python :: 3.8
Classifier: Programming Language :: Python :: 3.9
Classifier: Programming Language :: Python :: 3.10
Classifier: Topic :: Internet :: WWW/HTTP
Classifier: Topic :: Internet :: WWW/HTTP :: Dynamic Content
License-File: LICENCE
Requires-Dist: requests
Provides-Extra: docs
Requires-Dist: sphinx; extra == "docs"
Requires-Dist: sphinx-automodapi; extra == "docs"
